psnake/psnake.py
psnake-0.0.1.dist-info/LICENSE
psnake-0.0.1.dist-info/METADATA
psnake-0.0.1.dist-info/WHEEL
psnake-0.0.1.dist-info/entry_points.txt
psnake-0.0.1.dist-info/top_level.txt
psnake-0.0.1.dist-info/RECORD
