Metadata-Version: 2.1
Name: psnake
Version: 0.0.1
Summary: Simple snake game with Python
Home-page: https://github.com/berk-karaal/psnake
Author: Berk Karaal
Author-email: iletisim.berkkaraal@gmail.com
License: UNKNOWN
Platform: UNKNOWN
Classifier: Programming Language :: Python :: 3
Classifier: License :: OSI Approved :: MIT License
Classifier: Operating System :: OS Independent
Requires-Python: >=3.8
License-File: LICENSE
